wasdi/__init__.py
wasdi/waspyLogFormatter.py
wasdi-0.8.7.7.dist-info/LICENSE
wasdi-0.8.7.7.dist-info/METADATA
wasdi-0.8.7.7.dist-info/WHEEL
wasdi-0.8.7.7.dist-info/top_level.txt
wasdi-0.8.7.7.dist-info/RECORD
