Metadata-Version: 2.2
Name: wasdi
Version: 0.8.7.7
Summary: The WASDI Python library
Home-page: https://www.wasdi.net
Author: WASDI Sarl
Author-email: info@wasdi.cloud
License: CC-BY License
Project-URL: Source, https://github.com/fadeoutsoftware/WASDI/tree/develop/libraries/waspy
Project-URL: Tracker, https://github.com/fadeoutsoftware/WASDI/issues
Classifier: Development Status :: 4 - Beta
Classifier: Environment :: Console
Classifier: Intended Audience :: Developers
Classifier: Intended Audience :: Science/Research
Classifier: License :: Other/Proprietary License
Classifier: Operating System :: OS Independent
Classifier: Programming Language :: Python :: 3
Classifier: Topic :: Scientific/Engineering
Classifier: Topic :: Scientific/Engineering :: Atmospheric Science
Classifier: Topic :: Scientific/Engineering :: GIS
Classifier: Topic :: Scientific/Engineering :: Image Processing
Classifier: Topic :: Software Development :: Libraries
License-File: LICENSE
Requires-Dist: requests
Dynamic: author
Dynamic: author-email
Dynamic: classifier
Dynamic: description
Dynamic: description-content-type
Dynamic: home-page
Dynamic: license
Dynamic: project-url
Dynamic: requires-dist
Dynamic: summary
